{"data":[{"CourseName":"Appium","PurchasedDate":"2023-12-16","Amount":99,"Location":"Asia"},{"CourseName":"WebServices","PurchasedDate":"2023-12-16","Amount":21,"Location":"Asia"},{"CourseName":"Jmeter","PurchasedDate":"2023-12-16","Amount":76,"Location":"Asia"},{"CourseName":"SDET","PurchasedDate":"2023-12-17","Amount":76,"Location":"Asia"},{"CourseName":"Angular","PurchasedDate":"2023-12-17","Amount":86,"Location":"Asia"},{"CourseName":"Tester","PurchasedDate":"2023-12-17","Amount":96,"Location":"Asia"},{"CourseName":"Crest","PurchasedDate":"2023-12-22","Amount":98,"Location":"Asia"}]}